<library id="solr" dir="org.apache.solr">
	<package id="solr" name="org.apache.solr">
		<maven>
			<groupId>org.apache.solr</groupId>
			<artifactId>solr-core</artifactId>
		</maven>
	</package>
	<package id="solr-common" name="org.apache.solr.common">
		<maven>
			<groupId>org.apache.solr</groupId>
			<artifactId>solr-solrj</artifactId>
		</maven>
	</package>
	<version>1.4</version>
	<release>0</release>
	<distributions>
		<distribution id="classic" />
	</distributions>
	<homeUri>
		http://lucene.apache.org/solr/
	</homeUri>
	<downloadUri>
		http://www.apache.org/dyn/closer.cgi/lucene/solr/
	</downloadUri>
	<javadocs>
		<link href="http://lucene.apache.org/solr/api/" />
	</javadocs>
</library>
